Workbook

Sheet FRESHMART SALES DASHBOARD
B2: FRESHMART SALES DASHBOARD
B6: STORE ID | F6: TOTAL SALES | J6: TOTAL PROFIT | N6: TOTAL QUANTITY | R6: TOTAL ORDERS
B7: All
F8: =Calculations!E2 -> 12948633 | J8: =Calculations!E3 -> 2037319.9 | N8: =Calculations!E4 -> 8323 | R8: =Calculations!E5 -> 2490
B11: PAYMENT MODE | F11: MONTHLY SALES TREND | K11: SALES BY PAYMENT MODE | P11: SALES BY SALES CHANNEL
C13: All
B16: SALES CHANNEL
B17: All
F21: PROFIT BY PRODUCT (TOP 10) | K21: SALES BY STORE (TOP 10) | P21: SALES BY PRODUCT CATEGORY

Sheet Data
A1: Month | B1: Sales | D1: Payment Mode | E1: Sales % | G1: Sales Channel | H1: Sales | J1: Product | K1: Profit | M1: Store | N1: Sales | P1: Category | Q1: Sales | S1: KPI | T1: Value | V1: Other Payment | W1: Share
A2: Apr-2024 | B2: 360000 | D2: Cash | E2: 22 | G2: Offline | H2: 62067324 | J2: Product 1 | K2: 46739 | M2: Store 1 | N2: 8652114 | P2: Category 1 | Q2: 2821365 | S2: Total Sales | T2: 12948633 | V2: Other 1 | W2: 3
A3: May-2024 | B3: 410000 | D3: Credit Card | E3: 20 | G3: Online | H3: 29910824 | J3: Product 2 | K3: 37844 | M3: Store 2 | N3: 7826323 | P3: Category 2 | Q3: 2065964 | S3: Total Profit | T3: 2037319.9 | V3: Other 2 | W3: 2
A4: Jun-2024 | B4: 395000 | D4: Debit Card | E4: 19 | J4: Product 3 | K4: 26857 | M4: Store 3 | N4: 7496647 | P4: Category 3 | Q4: 1858745 | S4: Total Quantity | T4: 8323 | V4: Other 3 | W4: 2
A5: Jul-2024 | B5: 520000 | D5: EMI | E5: 16 | J5: Product 4 | K5: 23678 | M5: Store 4 | N5: 6828325 | P5: Category 4 | Q5: 1624891 | S5: Total Orders | T5: 2490
A6: Aug-2024 | B6: 510000 | D6: Net Banking | E6: 9 | J6: Product 5 | K6: 22915 | M6: Store 5 | N6: 6390189 | P6: Category 5 | Q6: 1247558
A7: Sep-2024 | B7: 680000 | D7: UPI | E7: 7 | J7: Product 6 | K7: 21073 | M7: Store 6 | N7: 6231261 | P7: Category 6 | Q7: 932114
A8: Oct-2024 | B8: 1080000 | J8: Product 7 | K8: 18560 | M8: Store 7 | N8: 5943188 | P8: Category 7 | Q8: 712368
A9: Nov-2024 | B9: 700000 | J9: Product 8 | K9: 17964 | M9: Store 8 | N9: 5683364 | P9: Category 8 | Q9: 561285
A10: Dec-2024 | B10: 375000 | J10: Product 9 | K10: 16485 | M10: Store 9 | N10: 5754919
A11: Jan-2025 | B11: 365000 | J11: Product 10 | K11: 11142 | M11: Store 10 | N11: 5473274
A12: Feb-2025 | B12: 350000
A13: Mar-2025 | B13: 315000

Sheet Calculations
A1: Filter Values | D1: KPI | E1: Value | G1: Month | H1: Sales | J1: Payment Mode | K1: Share | M1: Channel | N1: Sales | P1: Product | Q1: Profit | S1: Store | T1: Sales | V1: Category | W1: Sales
A2: Store ID | B2: ='FRESHMART SALES DASHBOARD'!B7 -> All | D2: Total Sales | E2: =IF(AND(B2="All",B3="All",B4="All"),Data!T2,Data!T2) -> 12948633 | G2: Apr-2024 | H2: =Data!B2 -> 360000 | J2: Cash | K2: =Data!E2 -> 22 | M2: =Data!G2 -> Offline | N2: =Data!H2 -> 62067324 | P2: =Data!J2 -> Product 1 | Q2: =Data!K2 -> 46739 | S2: =Data!M2 -> Store 1 | T2: =Data!N2 -> 8652114 | V2: =Data!P2 -> Category 1 | W2: =Data!Q2 -> 2821365
A3: Payment Mode | B3: ='FRESHMART SALES DASHBOARD'!C13 -> All | D3: Total Profit | E3: =Data!T3 -> 2037319.9 | G3: May-2024 | H3: =Data!B3 -> 410000 | J3: Credit Card | K3: =Data!E3 -> 20 | M3: =Data!G3 -> Online | N3: =Data!H3 -> 29910824 | P3: =Data!J3 -> Product 2 | Q3: =Data!K3 -> 37844 | S3: =Data!M3 -> Store 2 | T3: =Data!N3 -> 7826323 | V3: =Data!P3 -> Category 2 | W3: =Data!Q3 -> 2065964
A4: Sales Channel | B4: ='FRESHMART SALES DASHBOARD'!B17 -> All | D4: Total Quantity | E4: =Data!T4 -> 8323 | G4: Jun-2024 | H4: =Data!B4 -> 395000 | J4: Debit Card | K4: =Data!E4 -> 19 | P4: =Data!J4 -> Product 3 | Q4: =Data!K4 -> 26857 | S4: =Data!M4 -> Store 3 | T4: =Data!N4 -> 7496647 | V4: =Data!P4 -> Category 3 | W4: =Data!Q4 -> 1858745
D5: Total Orders | E5: =Data!T5 -> 2490 | G5: Jul-2024 | H5: =Data!B5 -> 520000 | J5: EMI | K5: =Data!E5 -> 16 | P5: =Data!J5 -> Product 4 | Q5: =Data!K5 -> 23678 | S5: =Data!M5 -> Store 4 | T5: =Data!N5 -> 6828325 | V5: =Data!P5 -> Category 4 | W5: =Data!Q5 -> 1624891
G6: Aug-2024 | H6: =Data!B6 -> 510000 | J6: Net Banking | K6: =Data!E6 -> 9 | P6: =Data!J6 -> Product 5 | Q6: =Data!K6 -> 22915 | S6: =Data!M6 -> Store 5 | T6: =Data!N6 -> 6390189 | V6: =Data!P6 -> Category 5 | W6: =Data!Q6 -> 1247558
G7: Sep-2024 | H7: =Data!B7 -> 680000 | J7: UPI | K7: =Data!E7 -> 7 | P7: =Data!J7 -> Product 6 | Q7: =Data!K7 -> 21073 | S7: =Data!M7 -> Store 6 | T7: =Data!N7 -> 6231261 | V7: =Data!P7 -> Category 6 | W7: =Data!Q7 -> 932114
G8: Oct-2024 | H8: =Data!B8 -> 1080000 | J8: Other 1 | K8: =Data!W2 -> 3 | P8: =Data!J8 -> Product 7 | Q8: =Data!K8 -> 18560 | S8: =Data!M8 -> Store 7 | T8: =Data!N8 -> 5943188 | V8: =Data!P8 -> Category 7 | W8: =Data!Q8 -> 712368
G9: Nov-2024 | H9: =Data!B9 -> 700000 | J9: Other 2 | K9: =Data!W3 -> 2 | P9: =Data!J9 -> Product 8 | Q9: =Data!K9 -> 17964 | S9: =Data!M9 -> Store 8 | T9: =Data!N9 -> 5683364 | V9: =Data!P9 -> Category 8 | W9: =Data!Q9 -> 561285
G10: Dec-2024 | H10: =Data!B10 -> 375000 | J10: Other 3 | K10: =Data!W4 -> 2 | P10: =Data!J10 -> Product 9 | Q10: =Data!K10 -> 16485 | S10: =Data!M10 -> Store 9 | T10: =Data!N10 -> 5754919
G11: Jan-2025 | H11: =Data!B11 -> 365000 | P11: =Data!J11 -> Product 10 | Q11: =Data!K11 -> 11142 | S11: =Data!M11 -> Store 10 | T11: =Data!N11 -> 5473274
G12: Feb-2025 | H12: =Data!B12 -> 350000
G13: Mar-2025 | H13: =Data!B13 -> 315000
